odoo/addons/l10n_it_riba_oca/README.rst
odoo/addons/l10n_it_riba_oca/__init__.py
odoo/addons/l10n_it_riba_oca/__manifest__.py
odoo/addons/l10n_it_riba_oca/hooks.py
odoo/addons/l10n_it_riba_oca/data/riba_sequence.xml
odoo/addons/l10n_it_riba_oca/demo/riba_demo.xml
odoo/addons/l10n_it_riba_oca/i18n/it.po
odoo/addons/l10n_it_riba_oca/i18n/l10n_it_riba.pot
odoo/addons/l10n_it_riba_oca/i18n/l10n_it_riba_oca.pot
odoo/addons/l10n_it_riba_oca/migrations/18.0.1.0.0/pre-migrate.py
odoo/addons/l10n_it_riba_oca/models/__init__.py
odoo/addons/l10n_it_riba_oca/models/account.py
odoo/addons/l10n_it_riba_oca/models/account_config.py
odoo/addons/l10n_it_riba_oca/models/ir_ui_menu.py
odoo/addons/l10n_it_riba_oca/models/partner.py
odoo/addons/l10n_it_riba_oca/models/riba.py
odoo/addons/l10n_it_riba_oca/models/riba_config.py
odoo/addons/l10n_it_riba_oca/readme/CONFIGURE.md
odoo/addons/l10n_it_riba_oca/readme/CONTRIBUTORS.md
odoo/addons/l10n_it_riba_oca/readme/DESCRIPTION.md
odoo/addons/l10n_it_riba_oca/readme/USAGE.md
odoo/addons/l10n_it_riba_oca/report/__init__.py
odoo/addons/l10n_it_riba_oca/report/report.xml
odoo/addons/l10n_it_riba_oca/report/slip_qweb.py
odoo/addons/l10n_it_riba_oca/security/ir.model.access.csv
odoo/addons/l10n_it_riba_oca/security/riba_security.xml
odoo/addons/l10n_it_riba_oca/static/description/icon.png
odoo/addons/l10n_it_riba_oca/static/description/index.html
odoo/addons/l10n_it_riba_oca/tests/__init__.py
odoo/addons/l10n_it_riba_oca/tests/riba_common.py
odoo/addons/l10n_it_riba_oca/tests/test_account_move.py
odoo/addons/l10n_it_riba_oca/tests/test_menu.py
odoo/addons/l10n_it_riba_oca/tests/test_riba.py
odoo/addons/l10n_it_riba_oca/views/account_config_view.xml
odoo/addons/l10n_it_riba_oca/views/account_view.xml
odoo/addons/l10n_it_riba_oca/views/configuration_view.xml
odoo/addons/l10n_it_riba_oca/views/partner_view.xml
odoo/addons/l10n_it_riba_oca/views/riba_detail_view.xml
odoo/addons/l10n_it_riba_oca/views/riba_view.xml
odoo_addon_l10n_it_riba_oca-18.0.1.1.0.dist-info/METADATA
odoo_addon_l10n_it_riba_oca-18.0.1.1.0.dist-info/WHEEL
odoo_addon_l10n_it_riba_oca-18.0.1.1.0.dist-info/top_level.txt
odoo_addon_l10n_it_riba_oca-18.0.1.1.0.dist-info/RECORD
