Metadata-Version: 2.1
Name: odoo-addon-l10n_it_riba_oca
Version: 18.0.1.1.0
Requires-Python: >=3.10
Requires-Dist: odoo-addon-account_due_list==18.0.*
Requires-Dist: odoo-addon-account_payment_term_extension==18.0.*
Requires-Dist: odoo-addon-l10n_it_abicab==18.0.*
Requires-Dist: odoo-addon-l10n_it_edi_related_document==18.0.*
Requires-Dist: odoo==18.0.*
Requires-Dist: openupgradelib
Requires-Dist: unidecode
Summary: Ricevute bancarie
Home-page: https://github.com/OCA/l10n-italy
License: AGPL-3
Author: Odoo Community Association (OCA)
Author-email: support@odoo-community.org
Classifier: Programming Language :: Python
Classifier: Framework :: Odoo
Classifier: Framework :: Odoo :: 18.0
Classifier: License :: OSI Approved :: GNU Affero General Public License v3
Classifier: Development Status :: 4 - Beta
